AUTHORS
CHANGELOG.txt
DESCRIPTION
LICENSE
MANIFEST.in
setup.py
django_social_media_links.egg-info/PKG-INFO
django_social_media_links.egg-info/SOURCES.txt
django_social_media_links.egg-info/dependency_links.txt
django_social_media_links.egg-info/requires.txt
django_social_media_links.egg-info/top_level.txt
social_media_links/__init__.py
social_media_links/admin.py
social_media_links/models.py
social_media_links/urls.py
social_media_links/views.py
social_media_links/migrations/0001_initial.py
social_media_links/migrations/0002_auto__add_field_link_position.py
social_media_links/migrations/0003_auto__add_field_linktype_image.py
social_media_links/migrations/__init__.py
social_media_links/static/social_media_links/css/MonoSocialIconsFont-1.10.eot
social_media_links/static/social_media_links/css/MonoSocialIconsFont-1.10.otf
social_media_links/static/social_media_links/css/MonoSocialIconsFont-1.10.svg
social_media_links/static/social_media_links/css/MonoSocialIconsFont-1.10.ttf
social_media_links/static/social_media_links/css/MonoSocialIconsFont-1.10.woff
social_media_links/static/social_media_links/css/styles.css
social_media_links/templates/social_media_links/partials/link_list.html
social_media_links/templatetags/__init__.py
social_media_links/templatetags/social_media_links_tags.py
social_media_links/tests/__init__.py
social_media_links/tests/factories.py
social_media_links/tests/models_tests.py
social_media_links/tests/runtests.py
social_media_links/tests/social_media_links_tags_tests.py
social_media_links/tests/south_settings.py
social_media_links/tests/test_settings.py
social_media_links/tests/urls.py
social_media_links/tests/test_app/__init__.py
social_media_links/tests/test_app/models.py
social_media_links/tests/test_app/templates/400.html
social_media_links/tests/test_app/templates/500.html
social_media_links/tests/test_app/templates/home.html