Metadata-Version: 1.0
Name: django-social-media-links
Version: 0.2
Summary: A reusable Django app that renders a set of social media links, i.e. for your website footer.
